checkout/__init__.py
checkout/cases/__init__.py
checkout/cases/redirect_response_mock.py
checkout/checkout.py
checkout/clients/__init__.py
checkout/clients/authentication.py
checkout/clients/http_client.py
checkout/clients/rest_client.py
checkout/contracts/__init__.py
checkout/contracts/carrier.py
checkout/decorators/convert_to_boolean.py
checkout/decorators/filter_empty_values.py
checkout/entities/__init__.py
checkout/entities/account.py
checkout/entities/address.py
checkout/entities/amount.py
checkout/entities/amount_base.py
checkout/entities/amount_conversion.py
checkout/entities/amount_detail.py
checkout/entities/credit.py
checkout/entities/discount.py
checkout/entities/dispersion_payment.py
checkout/entities/instrument.py
checkout/entities/item.py
checkout/entities/name_value_pair.py
checkout/entities/payment.py
checkout/entities/payment_modifier.py
checkout/entities/person.py
checkout/entities/recurring.py
checkout/entities/settings.py
checkout/entities/status.py
checkout/entities/subscription.py
checkout/entities/subscription_information.py
checkout/entities/tax_detail.py
checkout/entities/token.py
checkout/entities/transaction.py
checkout/enums/__init__.py
checkout/enums/display_on_enum.py
checkout/enums/status_enum.py
checkout/exceptions/__init__.py
checkout/exceptions/checkout_exception.py
checkout/exceptions/http_exceptions.py
checkout/messages/__init__.py
checkout/messages/requests/__init__ copy.py
checkout/messages/requests/__init__.py
checkout/messages/requests/collect.py
checkout/messages/requests/invalidate_token.py
checkout/messages/requests/redirect.py
checkout/messages/responses/__init__.py
checkout/messages/responses/information.py
checkout/messages/responses/redirect.py
checkout/messages/responses/reverse.py
checkout/mixins/fields_mixin.py
checkout/mixins/logger.py
checkout/tests/__init__.py
checkout/tests/feature/test_checkout.py
checkout/tests/mocks/responses/collect_response_fails_token_not_valid.json
checkout_p2p-1.0.0.dist-info/LICENSE.txt
checkout_p2p-1.0.0.dist-info/METADATA
checkout_p2p-1.0.0.dist-info/WHEEL
checkout_p2p-1.0.0.dist-info/RECORD
