Metadata-Version: 2.1
Name: checkout-p2p
Version: 1.0.0
Summary: Python library for PlaceToPay Checkout integration.
Home-page: https://github.com/andrextor/python-checkout
License: MIT
Author: Iván Andrés López Gómez
Author-email: andresgom11012@gmail.com
Requires-Python: >=3.13,<4.0
Classifier: License :: OSI Approved :: MIT License
Classifier: Programming Language :: Python :: 3
Classifier: Programming Language :: Python :: 3.13
Requires-Dist: annotated-types (==0.7.0)
Requires-Dist: certifi (==2024.8.30)
Requires-Dist: charset-normalizer (==3.4.0)
Requires-Dist: idna (==3.10)
Requires-Dist: iniconfig (==2.0.0)
Requires-Dist: packaging (==24.2)
Requires-Dist: pluggy (==1.5.0)
Requires-Dist: pydantic (==2.10.0)
Requires-Dist: pydantic-core (==2.27.0)
Requires-Dist: python-dotenv (==1.0.1)
Requires-Dist: requests (==2.32.3)
Requires-Dist: setuptools (==75.6.0)
Requires-Dist: typing-extensions (==4.12.2)
Requires-Dist: urllib3 (==2.2.3)
Project-URL: homepage, https://github.com/andrextor/python-checkout/wiki
Project-URL: repository, https://github.com/andrextor/python-checkout
